tests/__init__.py
tests/test_asyncio.py
tests/test_browser_apis.py
tests/test_bz2.py
tests/test_canvas.py
tests/test_cmdline_runner.py
tests/test_common.py
tests/test_compat.py
tests/test_console.py
tests/test_core_python.py
tests/test_filesystem.py
tests/test_jsproxy.py
tests/test_package_loading.py
tests/test_pyodide.py
tests/test_pyodide_http.py
tests/test_pyproxy.py
tests/test_pytest_wrapper.py
tests/test_python.py
tests/test_python_esm.py
tests/test_snapshots.py
tests/test_stack_switching.py
tests/test_static_typing.py
tests/test_stdlib_fixes.py
tests/test_streams.py
tests/test_typeconversions.py
tests/test_webloop.py
tests/test_webloop_webworker.py
tests/test_webworker.py
tests/test_pkg/__init__.py
tests/test_pkg/some_module.py
pyodidesafernicolas-0.1.0.dist-info/LICENSE
pyodidesafernicolas-0.1.0.dist-info/METADATA
pyodidesafernicolas-0.1.0.dist-info/WHEEL
pyodidesafernicolas-0.1.0.dist-info/top_level.txt
pyodidesafernicolas-0.1.0.dist-info/RECORD
