Metadata-Version: 2.2
Name: pyodidesafernicolas
Version: 0.1.0
Summary: Pyodide with no access to browser through python code
Home-page: https://github.com/nicolasjesse/pyodide
Author: Nicolas Jesse
Author-email: nicolasnekar@gmail.com
Classifier: Programming Language :: Python :: 3
Classifier: License :: OSI Approved :: MIT License
Classifier: Operating System :: OS Independent
Requires-Python: >=3.6
License-File: LICENSE
